{
  "model": "EleutherAI/pythia-410m",
  "L": 128,
  "rows": [
    {
      "rev": "step0",
      "step": 0,
      "induction": 0.006353502161800861,
      "head": [
        15,
        3
      ]
    },
    {
      "rev": "step1",
      "step": 1,
      "induction": 0.006353502161800861,
      "head": [
        15,
        3
      ]
    },
    {
      "rev": "step2",
      "step": 2,
      "induction": 0.006357698701322079,
      "head": [
        15,
        3
      ]
    },
    {
      "rev": "step4",
      "step": 4,
      "induction": 0.006520302500575781,
      "head": [
        15,
        3
      ]
    },
    {
      "rev": "step8",
      "step": 8,
      "induction": 0.007031084969639778,
      "head": [
        15,
        3
      ]
    },
    {
      "rev": "step16",
      "step": 16,
      "induction": 0.0075391801074147224,
      "head": [
        12,
        6
      ]
    },
    {
      "rev": "step32",
      "step": 32,
      "induction": 0.008216376416385174,
      "head": [
        12,
        6
      ]
    },
    {
      "rev": "step64",
      "step": 64,
      "induction": 0.006878422107547522,
      "head": [
        19,
        5
      ]
    },
    {
      "rev": "step128",
      "step": 128,
      "induction": 0.006313007790595293,
      "head": [
        19,
        14
      ]
    },
    {
      "rev": "step256",
      "step": 256,
      "induction": 0.006465179845690727,
      "head": [
        12,
        6
      ]
    },
    {
      "rev": "step512",
      "step": 512,
      "induction": 0.008736678399145603,
      "head": [
        11,
        1
      ]
    },
    {
      "rev": "step1000",
      "step": 1000,
      "induction": 0.9056302905082703,
      "head": [
        11,
        14
      ]
    },
    {
      "rev": "step2000",
      "step": 2000,
      "induction": 0.9083607792854309,
      "head": [
        11,
        14
      ]
    },
    {
      "rev": "step4000",
      "step": 4000,
      "induction": 0.9501307606697083,
      "head": [
        8,
        6
      ]
    },
    {
      "rev": "step8000",
      "step": 8000,
      "induction": 0.9785979390144348,
      "head": [
        8,
        6
      ]
    },
    {
      "rev": "step16000",
      "step": 16000,
      "induction": 0.9812658429145813,
      "head": [
        8,
        6
      ]
    },
    {
      "rev": "step32000",
      "step": 32000,
      "induction": 0.9863030314445496,
      "head": [
        8,
        6
      ]
    },
    {
      "rev": "step64000",
      "step": 64000,
      "induction": 0.9819762706756592,
      "head": [
        8,
        6
      ]
    },
    {
      "rev": "step128000",
      "step": 128000,
      "induction": 0.974866509437561,
      "head": [
        8,
        6
      ]
    },
    {
      "rev": "step143000",
      "step": 143000,
      "induction": 0.9774156212806702,
      "head": [
        8,
        6
      ]
    }
  ]
}